<annotation>
	<folder></folder>
	<filename>0041_jpg.rf.3d715265b59d7b2169a4093cfba4874a.jpg</filename>
	<path>0041_jpg.rf.3d715265b59d7b2169a4093cfba4874a.jpg</path>
	<source>
		<database>roboflow.com</database>
	</source>
	<size>
		<width>640</width>
		<height>640</height>
		<depth>3</depth>
	</size>
	<segmented>0</segmented>
	<object>
		<name>ESP32</name>
		<pose>Unspecified</pose>
		<truncated>0</truncated>
		<difficult>0</difficult>
		<occluded>0</occluded>
		<bndbox>
			<xmin>431</xmin>
			<xmax>627</xmax>
			<ymin>218</ymin>
			<ymax>418</ymax>
		</bndbox>
		<polygon>
			<x1>444</x1>
			<y1>259</y1>
			<x2>439</x2>
			<y2>266</y2>
			<x3>437</x3>
			<y3>354</y3>
			<x4>430</x4>
			<y4>386</y4>
			<x5>430</x5>
			<y5>398</y5>
			<x6>439</x6>
			<y6>414</y6>
			<x7>539</x7>
			<y7>417</y7>
			<x8>587</x8>
			<y8>413</y8>
			<x9>598</x9>
			<y9>416</y9>
			<x10>604</x10>
			<y10>413</y10>
			<x11>626</x11>
			<y11>237</y11>
			<x12>619</x12>
			<y12>231</y12>
			<x13>539</x13>
			<y13>218</y13>
			<x14>538</x14>
			<y14>217</y14>
			<x15>516</x15>
			<y15>225</y15>
			<x16>459</x16>
			<y16>226</y16>
			<x17>446</x17>
			<y17>238</y17>
			<x18>444</x18>
			<y18>259</y18>
		</polygon>
	</object>
	<object>
		<name>STM32</name>
		<pose>Unspecified</pose>
		<truncated>0</truncated>
		<difficult>0</difficult>
		<occluded>0</occluded>
		<bndbox>
			<xmin>171</xmin>
			<xmax>352</xmax>
			<ymin>209</ymin>
			<ymax>432</ymax>
		</bndbox>
		<polygon>
			<x1>207</x1>
			<y1>228</y1>
			<x2>210</x2>
			<y2>230</y2>
			<x3>210</x3>
			<y3>243</y3>
			<x4>191</x4>
			<y4>325</y4>
			<x5>188</x5>
			<y5>364</y5>
			<x6>170</x6>
			<y6>423</y6>
			<x7>247</x7>
			<y7>431</y7>
			<x8>318</x8>
			<y8>428</y8>
			<x9>333</x9>
			<y9>366</y9>
			<x10>334</x10>
			<y10>340</y10>
			<x11>351</x11>
			<y11>249</y11>
			<x12>350</x12>
			<y12>234</y12>
			<x13>346</x13>
			<y13>230</y13>
			<x14>326</x14>
			<y14>226</y14>
			<x15>319</x15>
			<y15>212</y15>
			<x16>288</x16>
			<y16>209</y16>
			<x17>278</x17>
			<y17>212</y17>
			<x18>271</x18>
			<y18>208</y18>
			<x19>270</x19>
			<y19>208</y19>
			<x20>263</x20>
			<y20>209</y20>
			<x21>256</x21>
			<y21>217</y21>
			<x22>223</x22>
			<y22>216</y22>
			<x23>207</x23>
			<y23>228</y23>
		</polygon>
	</object>
</annotation>
