<annotation>
	<folder></folder>
	<filename>14_jpg.rf.1c840a718bbc961835dca754227491e6.jpg</filename>
	<path>14_jpg.rf.1c840a718bbc961835dca754227491e6.jpg</path>
	<source>
		<database>roboflow.com</database>
	</source>
	<size>
		<width>640</width>
		<height>640</height>
		<depth>3</depth>
	</size>
	<segmented>0</segmented>
	<object>
		<name>Raspberry-Pi-4-B</name>
		<pose>Unspecified</pose>
		<truncated>0</truncated>
		<difficult>0</difficult>
		<occluded>0</occluded>
		<bndbox>
			<xmin>101</xmin>
			<xmax>527</xmax>
			<ymin>48</ymin>
			<ymax>626</ymax>
		</bndbox>
		<polygon>
			<x1>292</x1>
			<y1>59</y1>
			<x2>115</x2>
			<y2>74</y2>
			<x3>106</x3>
			<y3>77</y3>
			<x4>100</x4>
			<y4>87</y4>
			<x5>137</x5>
			<y5>283</y5>
			<x6>152</x6>
			<y6>376</y6>
			<x7>153</x7>
			<y7>406</y7>
			<x8>161</x8>
			<y8>437</y8>
			<x9>161</x9>
			<y9>458</y9>
			<x10>168</x10>
			<y10>476</y10>
			<x11>166</x11>
			<y11>485</y11>
			<x12>185</x12>
			<y12>592</y12>
			<x13>199</x13>
			<y13>604</y13>
			<x14>204</x14>
			<y14>625</y14>
			<x15>301</x15>
			<y15>615</y15>
			<x16>300</x16>
			<y16>595</y16>
			<x17>303</x17>
			<y17>590</y17>
			<x18>326</x18>
			<y18>596</y18>
			<x19>328</x19>
			<y19>616</y19>
			<x20>413</x20>
			<y20>609</y20>
			<x21>411</x21>
			<y21>590</y21>
			<x22>417</x22>
			<y22>588</y22>
			<x23>421</x23>
			<y23>581</y23>
			<x24>431</x24>
			<y24>581</y24>
			<x25>436</x25>
			<y25>586</y25>
			<x26>440</x26>
			<y26>604</y26>
			<x27>521</x27>
			<y27>598</y27>
			<x28>524</x28>
			<y28>594</y28>
			<x29>520</x29>
			<y29>573</y29>
			<x30>526</x30>
			<y30>560</y30>
			<x31>522</x31>
			<y31>558</y31>
			<x32>519</x32>
			<y32>515</y32>
			<x33>500</x33>
			<y33>409</y33>
			<x34>505</x34>
			<y34>401</y34>
			<x35>516</x35>
			<y35>399</y35>
			<x36>516</x36>
			<y36>390</y36>
			<x37>511</x37>
			<y37>365</y37>
			<x38>498</x38>
			<y38>363</y38>
			<x39>490</x39>
			<y39>348</y39>
			<x40>486</x40>
			<y40>313</y40>
			<x41>494</x41>
			<y41>310</y41>
			<x42>494</x42>
			<y42>295</y42>
			<x43>490</x43>
			<y43>278</y43>
			<x44>486</x44>
			<y44>271</y44>
			<x45>479</x45>
			<y45>269</y45>
			<x46>473</x46>
			<y46>251</y46>
			<x47>471</x47>
			<y47>231</y47>
			<x48>480</x48>
			<y48>226</y48>
			<x49>481</x49>
			<y49>218</y49>
			<x50>473</x50>
			<y50>187</y50>
			<x51>462</x51>
			<y51>183</y51>
			<x52>456</x52>
			<y52>143</y52>
			<x53>463</x53>
			<y53>140</y53>
			<x54>463</x54>
			<y54>134</y54>
			<x55>456</x55>
			<y55>93</y55>
			<x56>443</x56>
			<y56>85</y56>
			<x57>439</x57>
			<y57>58</y57>
			<x58>428</x58>
			<y58>50</y58>
			<x59>303</x59>
			<y59>59</y59>
			<x60>298</x60>
			<y60>57</y60>
			<x61>296</x61>
			<y61>48</y61>
			<x62>284</x62>
			<y62>47</y62>
			<x63>283</x63>
			<y63>47</y63>
			<x64>263</x64>
			<y64>48</y64>
			<x65>293</x65>
			<y65>48</y65>
			<x66>296</x66>
			<y66>51</y66>
			<x67>292</x67>
			<y67>59</y67>
		</polygon>
	</object>
</annotation>
