<annotation>
	<folder></folder>
	<filename>19_JPG_jpg.rf.f2a1c72d182baef67087ee5638863821.jpg</filename>
	<path>19_JPG_jpg.rf.f2a1c72d182baef67087ee5638863821.jpg</path>
	<source>
		<database>roboflow.com</database>
	</source>
	<size>
		<width>640</width>
		<height>640</height>
		<depth>3</depth>
	</size>
	<segmented>0</segmented>
	<object>
		<name>Raspberry-Pi-2-B</name>
		<pose>Unspecified</pose>
		<truncated>0</truncated>
		<difficult>0</difficult>
		<occluded>0</occluded>
		<bndbox>
			<xmin>27</xmin>
			<xmax>640</xmax>
			<ymin>77</ymin>
			<ymax>589</ymax>
		</bndbox>
		<polygon>
			<x1>26</x1>
			<y1>401</y1>
			<x2>26</x2>
			<y2>412</y2>
			<x3>30</x3>
			<y3>418</y3>
			<x4>105</x4>
			<y4>471</y4>
			<x5>117</x5>
			<y5>474</y5>
			<x6>118</x6>
			<y6>485</y6>
			<x7>129</x7>
			<y7>482</y7>
			<x8>130</x8>
			<y8>488</y8>
			<x9>124</x9>
			<y9>491</y9>
			<x10>138</x10>
			<y10>492</y10>
			<x11>144</x11>
			<y11>498</y11>
			<x12>137</x12>
			<y12>501</y12>
			<x13>141</x13>
			<y13>504</y13>
			<x14>151</x14>
			<y14>502</y14>
			<x15>155</x15>
			<y15>506</y15>
			<x16>143</x16>
			<y16>511</y16>
			<x17>148</x17>
			<y17>516</y17>
			<x18>153</x18>
			<y18>515</y18>
			<x19>156</x19>
			<y19>522</y19>
			<x20>181</x20>
			<y20>536</y20>
			<x21>182</x21>
			<y21>541</y21>
			<x22>196</x22>
			<y22>551</y22>
			<x23>235</x23>
			<y23>557</y23>
			<x24>222</x24>
			<y24>561</y24>
			<x25>231</x25>
			<y25>564</y25>
			<x26>238</x26>
			<y26>561</y26>
			<x27>242</x27>
			<y27>569</y27>
			<x28>270</x28>
			<y28>587</y28>
			<x29>279</x29>
			<y29>588</y29>
			<x30>292</x30>
			<y30>580</y30>
			<x31>303</x31>
			<y31>586</y31>
			<x32>308</x32>
			<y32>583</y32>
			<x33>326</x33>
			<y33>588</y33>
			<x34>355</x34>
			<y34>588</y34>
			<x35>365</x35>
			<y35>581</y35>
			<x36>366</x36>
			<y36>573</y36>
			<x37>360</x37>
			<y37>566</y37>
			<x38>389</x38>
			<y38>542</y38>
			<x39>398</x39>
			<y39>544</y39>
			<x40>411</x40>
			<y40>556</y40>
			<x41>421</x41>
			<y41>555</y41>
			<x42>478</x42>
			<y42>507</y42>
			<x43>480</x43>
			<y43>498</y43>
			<x44>464</x44>
			<y44>483</y44>
			<x45>471</x45>
			<y45>475</y45>
			<x46>478</x46>
			<y46>472</y46>
			<x47>483</x47>
			<y47>480</y47>
			<x48>491</x48>
			<y48>481</y48>
			<x49>502</x49>
			<y49>473</y49>
			<x50>503</x50>
			<y50>458</y50>
			<x51>520</x51>
			<y51>461</y51>
			<x52>532</x52>
			<y52>457</y52>
			<x53>538</x53>
			<y53>460</y53>
			<x54>553</x54>
			<y54>451</y54>
			<x55>558</x55>
			<y55>442</y55>
			<x56>558</x56>
			<y56>430</y56>
			<x57>549</x57>
			<y57>413</y57>
			<x58>556</x58>
			<y58>407</y58>
			<x59>558</x59>
			<y59>397</y59>
			<x60>572</x60>
			<y60>411</y60>
			<x61>582</x61>
			<y61>415</y61>
			<x62>583</x62>
			<y62>421</y62>
			<x63>590</x63>
			<y63>421</y63>
			<x64>598</x64>
			<y64>411</y64>
			<x65>603</x65>
			<y65>411</y65>
			<x66>608</x66>
			<y66>402</y66>
			<x67>612</x67>
			<y67>404</y67>
			<x68>627</x68>
			<y68>391</y68>
			<x69>620</x69>
			<y69>388</y69>
			<x70>618</x70>
			<y70>383</y70>
			<x71>621</x71>
			<y71>379</y71>
			<x72>628</x72>
			<y72>379</y72>
			<x73>630</x73>
			<y73>388</y73>
			<x74>639</x74>
			<y74>379</y74>
			<x75>639</x75>
			<y75>289</y75>
			<x76>634</x76>
			<y76>285</y76>
			<x77>639</x77>
			<y77>279</y77>
			<x78>639</x78>
			<y78>260</y78>
			<x79>602</x79>
			<y79>228</y79>
			<x80>584</x80>
			<y80>225</y80>
			<x81>565</x81>
			<y81>202</y81>
			<x82>520</x82>
			<y82>166</y82>
			<x83>506</x83>
			<y83>162</y83>
			<x84>491</x84>
			<y84>151</y84>
			<x85>470</x85>
			<y85>125</y85>
			<x86>434</x86>
			<y86>96</y86>
			<x87>420</x87>
			<y87>86</y87>
			<x88>409</x88>
			<y88>85</y88>
			<x89>395</x89>
			<y89>76</y89>
			<x90>390</x90>
			<y90>76</y90>
			<x91>374</x91>
			<y91>78</y91>
			<x92>352</x92>
			<y92>96</y92>
			<x93>37</x93>
			<y93>386</y93>
			<x94>26</x94>
			<y94>401</y94>
		</polygon>
	</object>
</annotation>
