<annotation>
	<folder></folder>
	<filename>20220414_105049_jpg.rf.2a68334af8d36d75c91e49f7308a3be4.jpg</filename>
	<path>20220414_105049_jpg.rf.2a68334af8d36d75c91e49f7308a3be4.jpg</path>
	<source>
		<database>roboflow.com</database>
	</source>
	<size>
		<width>640</width>
		<height>640</height>
		<depth>3</depth>
	</size>
	<segmented>0</segmented>
	<object>
		<name>Jetson TX2</name>
		<pose>Unspecified</pose>
		<truncated>0</truncated>
		<difficult>0</difficult>
		<occluded>0</occluded>
		<bndbox>
			<xmin>118</xmin>
			<xmax>469</xmax>
			<ymin>194</ymin>
			<ymax>527</ymax>
		</bndbox>
		<polygon>
			<x1>300</x1>
			<y1>257</y1>
			<x2>288</x2>
			<y2>252</y2>
			<x3>251</x3>
			<y3>253</y3>
			<x4>249</x4>
			<y4>260</y4>
			<x5>241</x5>
			<y5>265</y5>
			<x6>238</x6>
			<y6>260</y6>
			<x7>223</x7>
			<y7>259</y7>
			<x8>219</x8>
			<y8>250</y8>
			<x9>178</x9>
			<y9>250</y9>
			<x10>171</x10>
			<y10>262</y10>
			<x11>153</x11>
			<y11>260</y11>
			<x12>150</x12>
			<y12>263</y12>
			<x13>129</x13>
			<y13>436</y13>
			<x14>118</x14>
			<y14>441</y14>
			<x15>118</x15>
			<y15>446</y15>
			<x16>126</x16>
			<y16>445</y16>
			<x17>128</x17>
			<y17>448</y17>
			<x18>125</x18>
			<y18>469</y18>
			<x19>122</x19>
			<y19>471</y19>
			<x20>117</x20>
			<y20>465</y20>
			<x21>126</x21>
			<y21>495</y21>
			<x22>124</x22>
			<y22>502</y22>
			<x23>127</x23>
			<y23>508</y23>
			<x24>121</x24>
			<y24>511</y24>
			<x25>124</x25>
			<y25>526</y25>
			<x26>133</x26>
			<y26>521</y26>
			<x27>136</x27>
			<y27>523</y27>
			<x28>141</x28>
			<y28>515</y28>
			<x29>151</x29>
			<y29>511</y29>
			<x30>226</x30>
			<y30>500</y30>
			<x31>328</x31>
			<y31>499</y31>
			<x32>361</x32>
			<y32>508</y32>
			<x33>365</x33>
			<y33>504</y33>
			<x34>368</x34>
			<y34>474</y34>
			<x35>373</x35>
			<y35>477</y35>
			<x36>388</x36>
			<y36>471</y36>
			<x37>390</x37>
			<y37>478</y37>
			<x38>407</x38>
			<y38>475</y38>
			<x39>407</x39>
			<y39>461</y39>
			<x40>430</x40>
			<y40>418</y40>
			<x41>468</x41>
			<y41>326</y41>
			<x42>465</x42>
			<y42>313</y42>
			<x43>455</x43>
			<y43>308</y43>
			<x44>461</x44>
			<y44>288</y44>
			<x45>458</x45>
			<y45>281</y45>
			<x46>451</x46>
			<y46>278</y46>
			<x47>441</x47>
			<y47>279</y47>
			<x48>433</x48>
			<y48>287</y48>
			<x49>416</x49>
			<y49>337</y49>
			<x50>408</x50>
			<y50>349</y50>
			<x51>385</x51>
			<y51>345</y51>
			<x52>376</x52>
			<y52>336</y52>
			<x53>351</x53>
			<y53>334</y53>
			<x54>345</x54>
			<y54>318</y54>
			<x55>340</x55>
			<y55>267</y55>
			<x56>336</x56>
			<y56>258</y56>
			<x57>329</x57>
			<y57>255</y57>
			<x58>335</x58>
			<y58>193</y58>
			<x59>331</x59>
			<y59>193</y59>
			<x60>327</x60>
			<y60>251</y60>
			<x61>323</x61>
			<y61>259</y61>
			<x62>311</x62>
			<y62>252</y62>
			<x63>300</x63>
			<y63>257</y63>
		</polygon>
	</object>
</annotation>
