<annotation>
	<folder></folder>
	<filename>20220414_105049_jpg.rf.c245845f82dcee6fb134800fe390568d.jpg</filename>
	<path>20220414_105049_jpg.rf.c245845f82dcee6fb134800fe390568d.jpg</path>
	<source>
		<database>roboflow.com</database>
	</source>
	<size>
		<width>640</width>
		<height>640</height>
		<depth>3</depth>
	</size>
	<segmented>0</segmented>
	<object>
		<name>Jetson TX2</name>
		<pose>Unspecified</pose>
		<truncated>0</truncated>
		<difficult>0</difficult>
		<occluded>0</occluded>
		<bndbox>
			<xmin>252</xmin>
			<xmax>529</xmax>
			<ymin>171</ymin>
			<ymax>519</ymax>
		</bndbox>
		<polygon>
			<x1>283</x1>
			<y1>181</y1>
			<x2>280</x2>
			<y2>197</y2>
			<x3>293</x3>
			<y3>209</y3>
			<x4>346</x4>
			<y4>227</y4>
			<x5>350</x5>
			<y5>231</y5>
			<x6>350</x6>
			<y6>240</y6>
			<x7>345</x7>
			<y7>255</y7>
			<x8>338</x8>
			<y8>261</y8>
			<x9>338</x9>
			<y9>281</y9>
			<x10>333</x10>
			<y10>289</y10>
			<x11>319</x11>
			<y11>294</y11>
			<x12>264</x12>
			<y12>301</y12>
			<x13>258</x13>
			<y13>305</y13>
			<x14>253</x14>
			<y14>370</y14>
			<x15>254</x15>
			<y15>386</y15>
			<x16>261</x16>
			<y16>395</y16>
			<x17>261</x17>
			<y17>408</y17>
			<x18>259</x18>
			<y18>418</y18>
			<x19>251</x19>
			<y19>423</y19>
			<x20>254</x20>
			<y20>423</y20>
			<x21>257</x21>
			<y21>434</y21>
			<x22>257</x22>
			<y22>446</y22>
			<x23>251</x23>
			<y23>452</y23>
			<x24>251</x24>
			<y24>461</y24>
			<x25>258</x25>
			<y25>462</y25>
			<x26>265</x26>
			<y26>474</y26>
			<x27>266</x27>
			<y27>478</y27>
			<x28>261</x28>
			<y28>483</y28>
			<x29>281</x29>
			<y29>492</y29>
			<x30>435</x30>
			<y30>509</y30>
			<x31>438</x31>
			<y31>476</y31>
			<x32>446</x32>
			<y32>510</y32>
			<x33>478</x33>
			<y33>516</y33>
			<x34>483</x34>
			<y34>513</y34>
			<x35>510</x35>
			<y35>518</y35>
			<x36>527</x36>
			<y36>516</y36>
			<x37>528</x37>
			<y37>481</y37>
			<x38>509</x38>
			<y38>278</y38>
			<x39>482</x39>
			<y39>273</y39>
			<x40>477</x40>
			<y40>233</y40>
			<x41>471</x41>
			<y41>229</y41>
			<x42>461</x42>
			<y42>236</y42>
			<x43>456</x43>
			<y43>229</y43>
			<x44>414</x44>
			<y44>207</y44>
			<x45>323</x45>
			<y45>170</y45>
			<x46>322</x46>
			<y46>170</y46>
			<x47>313</x47>
			<y47>175</y47>
			<x48>309</x48>
			<y48>183</y48>
			<x49>295</x49>
			<y49>179</y49>
			<x50>283</x50>
			<y50>181</y50>
		</polygon>
	</object>
</annotation>
