<annotation>
	<folder></folder>
	<filename>2B-30_jpg.rf.eb574d56b833b306fe497c75fa5c4e4c.jpg</filename>
	<path>2B-30_jpg.rf.eb574d56b833b306fe497c75fa5c4e4c.jpg</path>
	<source>
		<database>roboflow.com</database>
	</source>
	<size>
		<width>640</width>
		<height>640</height>
		<depth>3</depth>
	</size>
	<segmented>0</segmented>
	<object>
		<name>Raspberry-Pi-2-B</name>
		<pose>Unspecified</pose>
		<truncated>0</truncated>
		<difficult>0</difficult>
		<occluded>0</occluded>
		<bndbox>
			<xmin>164</xmin>
			<xmax>505</xmax>
			<ymin>49</ymin>
			<ymax>558</ymax>
		</bndbox>
		<polygon>
			<x1>204</x1>
			<y1>88</y1>
			<x2>205</x2>
			<y2>113</y2>
			<x3>202</x3>
			<y3>119</y3>
			<x4>207</x4>
			<y4>124</y4>
			<x5>202</x5>
			<y5>131</y5>
			<x6>207</x6>
			<y6>138</y6>
			<x7>200</x7>
			<y7>145</y7>
			<x8>200</x8>
			<y8>161</y8>
			<x9>204</x9>
			<y9>168</y9>
			<x10>198</x10>
			<y10>173</y10>
			<x11>201</x11>
			<y11>184</y11>
			<x12>197</x12>
			<y12>188</y12>
			<x13>202</x13>
			<y13>198</y13>
			<x14>196</x14>
			<y14>201</y14>
			<x15>201</x15>
			<y15>208</y15>
			<x16>196</x16>
			<y16>219</y16>
			<x17>201</x17>
			<y17>226</y17>
			<x18>196</x18>
			<y18>228</y18>
			<x19>200</x19>
			<y19>239</y19>
			<x20>195</x20>
			<y20>241</y20>
			<x21>194</x21>
			<y21>257</y21>
			<x22>199</x22>
			<y22>268</y22>
			<x23>193</x23>
			<y23>271</y23>
			<x24>200</x24>
			<y24>279</y24>
			<x25>192</x25>
			<y25>286</y25>
			<x26>200</x26>
			<y26>296</y26>
			<x27>191</x27>
			<y27>301</y27>
			<x28>195</x28>
			<y28>306</y28>
			<x29>191</x29>
			<y29>318</y29>
			<x30>196</x30>
			<y30>325</y30>
			<x31>191</x31>
			<y31>330</y31>
			<x32>199</x32>
			<y32>338</y32>
			<x33>189</x33>
			<y33>342</y33>
			<x34>195</x34>
			<y34>348</y34>
			<x35>192</x35>
			<y35>357</y35>
			<x36>201</x36>
			<y36>367</y36>
			<x37>197</x37>
			<y37>431</y37>
			<x38>167</x38>
			<y38>438</y38>
			<x39>163</x39>
			<y39>529</y39>
			<x40>249</x40>
			<y40>537</y40>
			<x41>272</x41>
			<y41>543</y41>
			<x42>347</x42>
			<y42>545</y42>
			<x43>357</x43>
			<y43>550</y43>
			<x44>421</x44>
			<y44>557</y44>
			<x45>456</x45>
			<y45>553</y45>
			<x46>461</x46>
			<y46>549</y46>
			<x47>462</x47>
			<y47>541</y47>
			<x48>473</x48>
			<y48>537</y48>
			<x49>477</x49>
			<y49>530</y49>
			<x50>484</x50>
			<y50>383</y50>
			<x51>498</x51>
			<y51>370</y51>
			<x52>497</x52>
			<y52>348</y52>
			<x53>487</x53>
			<y53>337</y53>
			<x54>490</x54>
			<y54>280</y54>
			<x55>495</x55>
			<y55>268</y55>
			<x56>498</x56>
			<y56>231</y56>
			<x57>498</x57>
			<y57>205</y57>
			<x58>494</x58>
			<y58>191</y58>
			<x59>496</x59>
			<y59>145</y59>
			<x60>504</x60>
			<y60>119</y60>
			<x61>498</x61>
			<y61>60</y61>
			<x62>487</x62>
			<y62>53</y62>
			<x63>276</x63>
			<y63>48</y63>
			<x64>270.9</x64>
			<y64>48</y64>
			<x65>222</x65>
			<y65>49</y65>
			<x66>215</x66>
			<y66>58</y66>
			<x67>215</x67>
			<y67>83</y67>
			<x68>204</x68>
			<y68>88</y68>
		</polygon>
	</object>
</annotation>
