<annotation>
	<folder></folder>
	<filename>3_JPG_jpg.rf.84eea071c667f7b689b406bc569a5fef.jpg</filename>
	<path>3_JPG_jpg.rf.84eea071c667f7b689b406bc569a5fef.jpg</path>
	<source>
		<database>roboflow.com</database>
	</source>
	<size>
		<width>640</width>
		<height>640</height>
		<depth>3</depth>
	</size>
	<segmented>0</segmented>
	<object>
		<name>Raspberry-Pi-2-B</name>
		<pose>Unspecified</pose>
		<truncated>0</truncated>
		<difficult>0</difficult>
		<occluded>0</occluded>
		<bndbox>
			<xmin>94</xmin>
			<xmax>515</xmax>
			<ymin>1</ymin>
			<ymax>620</ymax>
		</bndbox>
		<polygon>
			<x1>381</x1>
			<y1>0</y1>
			<x2>361</x2>
			<y2>4</y2>
			<x3>113</x3>
			<y3>60</y3>
			<x4>105</x4>
			<y4>64</y4>
			<x5>97</x5>
			<y5>75</y5>
			<x6>101</x6>
			<y6>104</y6>
			<x7>93</x7>
			<y7>110</y7>
			<x8>94</x8>
			<y8>136</y8>
			<x9>97</x9>
			<y9>150</y9>
			<x10>106</x10>
			<y10>156</y10>
			<x11>109</x11>
			<y11>163</y11>
			<x12>113</x12>
			<y12>197</y12>
			<x13>113</x13>
			<y13>215</y13>
			<x14>103</x14>
			<y14>221</y14>
			<x15>103</x15>
			<y15>238</y15>
			<x16>113</x16>
			<y16>309</y16>
			<x17>122</x17>
			<y17>309</y17>
			<x18>129</x18>
			<y18>321</y18>
			<x19>133</x19>
			<y19>366</y19>
			<x20>133</x20>
			<y20>380</y20>
			<x21>119</x21>
			<y21>389</y21>
			<x22>118</x22>
			<y22>404</y22>
			<x23>123</x23>
			<y23>419</y23>
			<x24>129</x24>
			<y24>419</y24>
			<x25>131</x25>
			<y25>415</y25>
			<x26>143</x26>
			<y26>428</y26>
			<x27>161</x27>
			<y27>578</y27>
			<x28>170</x28>
			<y28>591</y28>
			<x29>175</x29>
			<y29>619</y29>
			<x30>271</x30>
			<y30>599</y30>
			<x31>274</x31>
			<y31>596</y31>
			<x32>273</x32>
			<y32>570</y32>
			<x33>298</x33>
			<y33>562</y33>
			<x34>304</x34>
			<y34>568</y34>
			<x35>300</x35>
			<y35>587</y35>
			<x36>318</x36>
			<y36>588</y36>
			<x37>394</x37>
			<y37>569</y37>
			<x38>398</x38>
			<y38>560</y38>
			<x39>393</x39>
			<y39>554</y39>
			<x40>392</x40>
			<y40>544</y40>
			<x41>416</x41>
			<y41>536</y41>
			<x42>424</x42>
			<y42>543</y42>
			<x43>424</x43>
			<y43>548</y43>
			<x44>416</x44>
			<y44>555</y44>
			<x45>421</x45>
			<y45>562</y45>
			<x46>428</x46>
			<y46>559</y46>
			<x47>443</x47>
			<y47>561</y47>
			<x48>450</x48>
			<y48>556</y48>
			<x49>498</x49>
			<y49>549</y49>
			<x50>514</x50>
			<y50>541</y50>
			<x51>508</x51>
			<y51>440</y51>
			<x52>475</x52>
			<y52>202</y52>
			<x53>453</x53>
			<y53>0</y53>
			<x54>447.857143</x54>
			<y54>0</y54>
			<x55>381</x55>
			<y55>0</y55>
		</polygon>
	</object>
</annotation>
