<annotation>
	<folder></folder>
	<filename>A000056_01-iso_934x700_jpg.rf.a28afde530845e49ecf0476405b82072.jpg</filename>
	<path>A000056_01-iso_934x700_jpg.rf.a28afde530845e49ecf0476405b82072.jpg</path>
	<source>
		<database>roboflow.com</database>
	</source>
	<size>
		<width>640</width>
		<height>640</height>
		<depth>3</depth>
	</size>
	<segmented>0</segmented>
	<object>
		<name>Arduino-Due</name>
		<pose>Unspecified</pose>
		<truncated>0</truncated>
		<difficult>0</difficult>
		<occluded>0</occluded>
		<bndbox>
			<xmin>97</xmin>
			<xmax>568</xmax>
			<ymin>120</ymin>
			<ymax>476</ymax>
		</bndbox>
		<polygon>
			<x1>336</x1>
			<y1>162</y1>
			<x2>313</x2>
			<y2>177</y2>
			<x3>311</x3>
			<y3>182</y3>
			<x4>298</x4>
			<y4>187</y4>
			<x5>286</x5>
			<y5>202</y5>
			<x6>274</x6>
			<y6>208</y6>
			<x7>201</x7>
			<y7>269</y7>
			<x8>198</x8>
			<y8>266</y8>
			<x9>197</x9>
			<y9>271</y9>
			<x10>181</x10>
			<y10>285</y10>
			<x11>166</x11>
			<y11>294</y11>
			<x12>122</x12>
			<y12>334</y12>
			<x13>96</x13>
			<y13>351</y13>
			<x14>96</x14>
			<y14>358</y14>
			<x15>129</x15>
			<y15>377</y15>
			<x16>130</x16>
			<y16>383</y16>
			<x17>141</x17>
			<y17>393</y17>
			<x18>158</x18>
			<y18>401</y18>
			<x19>196</x19>
			<y19>433</y19>
			<x20>208</x20>
			<y20>436</y20>
			<x21>260</x21>
			<y21>474</y21>
			<x22>273</x22>
			<y22>475</y22>
			<x23>389</x23>
			<y23>381</y23>
			<x24>396</x24>
			<y24>368</y24>
			<x25>411</x25>
			<y25>363</y25>
			<x26>564</x26>
			<y26>239</y26>
			<x27>567</x27>
			<y27>232</y27>
			<x28>562</x28>
			<y28>215</y28>
			<x29>539</x29>
			<y29>202</y29>
			<x30>540</x30>
			<y30>197</y30>
			<x31>526</x31>
			<y31>193</y31>
			<x32>526</x32>
			<y32>188</y32>
			<x33>510</x33>
			<y33>181</y33>
			<x34>511</x34>
			<y34>177</y34>
			<x35>478</x35>
			<y35>162</y35>
			<x36>481</x36>
			<y36>158</y36>
			<x37>453</x37>
			<y37>144</y37>
			<x38>436</x38>
			<y38>144</y38>
			<x39>432</x39>
			<y39>141</y39>
			<x40>435</x40>
			<y40>138</y40>
			<x41>426</x41>
			<y41>137</y41>
			<x42>398</x42>
			<y42>119</y42>
			<x43>391</x43>
			<y43>119</y43>
			<x44>371</x44>
			<y44>132</y44>
			<x45>363</x45>
			<y45>142</y45>
			<x46>338</x46>
			<y46>156</y46>
			<x47>336</x47>
			<y47>162</y47>
		</polygon>
	</object>
</annotation>
