<annotation>
	<folder></folder>
	<filename>CDBA4_jpg.rf.4d86fe9416ba503f13e5db250d06456f.jpg</filename>
	<path>CDBA4_jpg.rf.4d86fe9416ba503f13e5db250d06456f.jpg</path>
	<source>
		<database>roboflow.com</database>
	</source>
	<size>
		<width>640</width>
		<height>640</height>
		<depth>3</depth>
	</size>
	<segmented>0</segmented>
	<object>
		<name>Arduino Mega 2560 -Yellow-</name>
		<pose>Unspecified</pose>
		<truncated>0</truncated>
		<difficult>0</difficult>
		<occluded>0</occluded>
		<bndbox>
			<xmin>74</xmin>
			<xmax>549</xmax>
			<ymin>49</ymin>
			<ymax>593</ymax>
		</bndbox>
		<polygon>
			<x1>128</x1>
			<y1>266</y1>
			<x2>121</x2>
			<y2>306</y2>
			<x3>81</x3>
			<y3>441</y3>
			<x4>73</x4>
			<y4>488</y4>
			<x5>88</x5>
			<y5>496</y5>
			<x6>106</x6>
			<y6>518</y6>
			<x7>163</x7>
			<y7>531</y7>
			<x8>376</x8>
			<y8>592</y8>
			<x9>388</x9>
			<y9>571</y9>
			<x10>399</x10>
			<y10>564</y10>
			<x11>404</x11>
			<y11>554</y11>
			<x12>417</x12>
			<y12>507</y12>
			<x13>433</x13>
			<y13>472</y13>
			<x14>435</x14>
			<y14>456</y14>
			<x15>451</x15>
			<y15>422</y15>
			<x16>456</x16>
			<y16>398</y16>
			<x17>461</x17>
			<y17>394</y17>
			<x18>475</x18>
			<y18>345</y18>
			<x19>483</x19>
			<y19>333</y19>
			<x20>513</x20>
			<y20>248</y20>
			<x21>514</x21>
			<y21>236</y21>
			<x22>522</x22>
			<y22>223</y22>
			<x23>548</x23>
			<y23>150</y23>
			<x24>548</x24>
			<y24>138</y24>
			<x25>521</x25>
			<y25>130</y25>
			<x26>518</x26>
			<y26>126</y26>
			<x27>500</x27>
			<y27>124</y27>
			<x28>498</x28>
			<y28>120</y28>
			<x29>491</x29>
			<y29>120</y29>
			<x30>488</x30>
			<y30>131</y30>
			<x31>489</x31>
			<y31>92</y31>
			<x32>456</x32>
			<y32>78</y32>
			<x33>420</x33>
			<y33>73</y33>
			<x34>413</x34>
			<y34>76</y34>
			<x35>398</x35>
			<y35>97</y35>
			<x36>313</x36>
			<y36>75</y36>
			<x37>297</x37>
			<y37>74</y37>
			<x38>235</x38>
			<y38>51</y38>
			<x39>198</x39>
			<y39>48</y39>
			<x40>195</x40>
			<y40>48</y40>
			<x41>186</x41>
			<y41>52</y41>
			<x42>181</x42>
			<y42>70</y42>
			<x43>153</x43>
			<y43>187</y43>
			<x44>128</x44>
			<y44>266</y44>
		</polygon>
	</object>
</annotation>
