<annotation>
	<folder></folder>
	<filename>IDAB1_jpg.rf.804bce81cc9dbd4fdc4a1f8787d14f02.jpg</filename>
	<path>IDAB1_jpg.rf.804bce81cc9dbd4fdc4a1f8787d14f02.jpg</path>
	<source>
		<database>roboflow.com</database>
	</source>
	<size>
		<width>640</width>
		<height>640</height>
		<depth>3</depth>
	</size>
	<segmented>0</segmented>
	<object>
		<name>Arduino Uno Camera Shield</name>
		<pose>Unspecified</pose>
		<truncated>0</truncated>
		<difficult>0</difficult>
		<occluded>0</occluded>
		<bndbox>
			<xmin>99</xmin>
			<xmax>535</xmax>
			<ymin>60</ymin>
			<ymax>582</ymax>
		</bndbox>
		<polygon>
			<x1>179</x1>
			<y1>94</y1>
			<x2>170</x2>
			<y2>145</y2>
			<x3>170</x3>
			<y3>155</y3>
			<x4>177</x4>
			<y4>163</y4>
			<x5>164</x5>
			<y5>229</y5>
			<x6>135</x6>
			<y6>241</y6>
			<x7>115</x7>
			<y7>350</y7>
			<x8>115</x8>
			<y8>361</y8>
			<x9>128</x9>
			<y9>367</y9>
			<x10>116</x10>
			<y10>372</y10>
			<x11>112</x11>
			<y11>379</y11>
			<x12>98</x12>
			<y12>462</y12>
			<x13>110</x13>
			<y13>467</y13>
			<x14>136</x14>
			<y14>458</y14>
			<x15>152</x15>
			<y15>479</y15>
			<x16>195</x16>
			<y16>496</y16>
			<x17>223</x17>
			<y17>512</y17>
			<x18>241</x18>
			<y18>514</y18>
			<x19>244</x19>
			<y19>518</y19>
			<x20>241</x20>
			<y20>523</y20>
			<x21>254</x21>
			<y21>521</y21>
			<x22>256</x22>
			<y22>530</y22>
			<x23>272</x23>
			<y23>527</y23>
			<x24>273</x24>
			<y24>536</y24>
			<x25>287</x25>
			<y25>532</y25>
			<x26>338</x26>
			<y26>550</y26>
			<x27>361</x27>
			<y27>545</y27>
			<x28>379</x28>
			<y28>550</y28>
			<x29>393</x29>
			<y29>557</y29>
			<x30>391</x30>
			<y30>576</y30>
			<x31>401</x31>
			<y31>581</y31>
			<x32>425</x32>
			<y32>570</y32>
			<x33>438</x33>
			<y33>569</y33>
			<x34>446</x34>
			<y34>563</y34>
			<x35>458</x35>
			<y35>496</y35>
			<x36>506</x36>
			<y36>286</y36>
			<x37>526</x37>
			<y37>218</y37>
			<x38>534</x38>
			<y38>171</y38>
			<x39>524</x39>
			<y39>164</y39>
			<x40>508</x40>
			<y40>162</y40>
			<x41>486</x41>
			<y41>153</y41>
			<x42>468</x42>
			<y42>153</y42>
			<x43>383</x43>
			<y43>126</y43>
			<x44>376</x44>
			<y44>118</y44>
			<x45>373</x45>
			<y45>120</y45>
			<x46>366</x46>
			<y46>114</y46>
			<x47>328</x47>
			<y47>103</y47>
			<x48>278</x48>
			<y48>82</y48>
			<x49>256</x49>
			<y49>68</y49>
			<x50>218</x50>
			<y50>59</y50>
			<x51>209</x51>
			<y51>59</y51>
			<x52>173</x52>
			<y52>68</y52>
			<x53>168</x53>
			<y53>76</y53>
			<x54>168</x54>
			<y54>87</y54>
			<x55>179</x55>
			<y55>94</y55>
		</polygon>
	</object>
</annotation>
