<annotation>
	<folder></folder>
	<filename>JABD2_jpg.rf.a6e9e3e29bee1b1e3a207c769e3687a6.jpg</filename>
	<path>JABD2_jpg.rf.a6e9e3e29bee1b1e3a207c769e3687a6.jpg</path>
	<source>
		<database>roboflow.com</database>
	</source>
	<size>
		<width>640</width>
		<height>640</height>
		<depth>3</depth>
	</size>
	<segmented>0</segmented>
	<object>
		<name>Arduino Uno -Black-</name>
		<pose>Unspecified</pose>
		<truncated>0</truncated>
		<difficult>0</difficult>
		<occluded>0</occluded>
		<bndbox>
			<xmin>73</xmin>
			<xmax>567</xmax>
			<ymin>46</ymin>
			<ymax>595</ymax>
		</bndbox>
		<polygon>
			<x1>156</x1>
			<y1>180</y1>
			<x2>126</x2>
			<y2>151</y2>
			<x3>119</x3>
			<y3>151</y3>
			<x4>72</x4>
			<y4>172</y4>
			<x5>76</x5>
			<y5>190</y5>
			<x6>90</x6>
			<y6>205</y6>
			<x7>79</x7>
			<y7>216</y7>
			<x8>82</x8>
			<y8>228</y8>
			<x9>120</x9>
			<y9>322</y9>
			<x10>126</x10>
			<y10>349</y10>
			<x11>206</x11>
			<y11>558</y11>
			<x12>224</x12>
			<y12>588</y12>
			<x13>242</x13>
			<y13>586</y13>
			<x14>261</x14>
			<y14>594</y14>
			<x15>471</x15>
			<y15>511</y15>
			<x16>492</x16>
			<y16>485</y16>
			<x17>549</x17>
			<y17>464</y17>
			<x18>559</x18>
			<y18>459</y18>
			<x19>566</x19>
			<y19>449</y19>
			<x20>553</x20>
			<y20>411</y20>
			<x21>407</x21>
			<y21>81</y21>
			<x22>391</x22>
			<y22>81</y22>
			<x23>348</x23>
			<y23>102</y23>
			<x24>340</x24>
			<y24>102</y24>
			<x25>334</x25>
			<y25>96</y25>
			<x26>311</x26>
			<y26>45</y26>
			<x27>307</x27>
			<y27>45</y27>
			<x28>240</x28>
			<y28>74</y28>
			<x29>263</x29>
			<y29>132</y29>
			<x30>261</x30>
			<y30>138</y30>
			<x31>156</x31>
			<y31>180</y31>
		</polygon>
	</object>
</annotation>
