<annotation>
	<folder></folder>
	<filename>JBBA4_jpg.rf.880a25e28feef7feb6fac3039b41a729.jpg</filename>
	<path>JBBA4_jpg.rf.880a25e28feef7feb6fac3039b41a729.jpg</path>
	<source>
		<database>roboflow.com</database>
	</source>
	<size>
		<width>640</width>
		<height>640</height>
		<depth>3</depth>
	</size>
	<segmented>0</segmented>
	<object>
		<name>Arduino Uno -Black-</name>
		<pose>Unspecified</pose>
		<truncated>0</truncated>
		<difficult>0</difficult>
		<occluded>0</occluded>
		<bndbox>
			<xmin>87</xmin>
			<xmax>552</xmax>
			<ymin>65</ymin>
			<ymax>579</ymax>
		</bndbox>
		<polygon>
			<x1>272</x1>
			<y1>112</y1>
			<x2>266</x2>
			<y2>118</y2>
			<x3>174</x3>
			<y3>132</y3>
			<x4>163</x4>
			<y4>132</y4>
			<x5>158</x5>
			<y5>128</y5>
			<x6>128</x6>
			<y6>131</y6>
			<x7>105</x7>
			<y7>138</y7>
			<x8>86</x8>
			<y8>156</y8>
			<x9>91</x9>
			<y9>199</y9>
			<x10>99</x10>
			<y10>203</y10>
			<x11>104</x11>
			<y11>213</y11>
			<x12>136</x12>
			<y12>313</y12>
			<x13>142</x13>
			<y13>322</y13>
			<x14>144</x14>
			<y14>333</y14>
			<x15>138</x15>
			<y15>357</y15>
			<x16>206</x16>
			<y16>556</y16>
			<x17>217</x17>
			<y17>578</y17>
			<x18>228</x18>
			<y18>576</y18>
			<x19>237</x19>
			<y19>551</y19>
			<x20>253</x20>
			<y20>557</y20>
			<x21>297</x21>
			<y21>556</y21>
			<x22>358</x22>
			<y22>544</y22>
			<x23>368</x23>
			<y23>553</y23>
			<x24>368</x24>
			<y24>561</y24>
			<x25>374</x25>
			<y25>548</y25>
			<x26>382</x26>
			<y26>548</y26>
			<x27>383</x27>
			<y27>560</y27>
			<x28>388</x28>
			<y28>546</y28>
			<x29>398</x29>
			<y29>544</y29>
			<x30>398</x30>
			<y30>558</y30>
			<x31>401</x31>
			<y31>558</y31>
			<x32>404</x32>
			<y32>545</y32>
			<x33>417</x33>
			<y33>534</y33>
			<x34>458</x34>
			<y34>530</y34>
			<x35>473</x35>
			<y35>514</y35>
			<x36>508</x36>
			<y36>508</y36>
			<x37>516</x37>
			<y37>511</y37>
			<x38>525</x38>
			<y38>536</y38>
			<x39>536</x39>
			<y39>535</y39>
			<x40>541</x40>
			<y40>524</y40>
			<x41>542</x41>
			<y41>507</y41>
			<x42>551</x42>
			<y42>494</y42>
			<x43>543</x43>
			<y43>456</y43>
			<x44>438</x44>
			<y44>91</y44>
			<x45>422</x45>
			<y45>88</y45>
			<x46>361</x46>
			<y46>96</y46>
			<x47>358</x47>
			<y47>101</y47>
			<x48>355</x48>
			<y48>96</y48>
			<x49>360</x49>
			<y49>68</y49>
			<x50>357</x50>
			<y50>64</y50>
			<x51>347</x51>
			<y51>64</y51>
			<x52>346</x52>
			<y52>64</y52>
			<x53>314</x53>
			<y53>67</y53>
			<x54>285</x54>
			<y54>76</y54>
			<x55>280</x55>
			<y55>82</y55>
			<x56>272</x56>
			<y56>112</y56>
		</polygon>
	</object>
</annotation>
