<annotation>
	<folder></folder>
	<filename>JDDB2_jpg.rf.6a1c78876d7a01c3108d1d8210b17016.jpg</filename>
	<path>JDDB2_jpg.rf.6a1c78876d7a01c3108d1d8210b17016.jpg</path>
	<source>
		<database>roboflow.com</database>
	</source>
	<size>
		<width>640</width>
		<height>640</height>
		<depth>3</depth>
	</size>
	<segmented>0</segmented>
	<object>
		<name>Arduino Uno -Black-</name>
		<pose>Unspecified</pose>
		<truncated>0</truncated>
		<difficult>0</difficult>
		<occluded>0</occluded>
		<bndbox>
			<xmin>78</xmin>
			<xmax>582</xmax>
			<ymin>51</ymin>
			<ymax>591</ymax>
		</bndbox>
		<polygon>
			<x1>109</x1>
			<y1>399</y1>
			<x2>95</x2>
			<y2>439</y2>
			<x3>91</x3>
			<y3>442</y3>
			<x4>77</x4>
			<y4>495</y4>
			<x5>82</x5>
			<y5>502</y5>
			<x6>95</x6>
			<y6>508</y6>
			<x7>104</x7>
			<y7>523</y7>
			<x8>121</x8>
			<y8>528</y8>
			<x9>321</x9>
			<y9>571</y9>
			<x10>345</x10>
			<y10>561</y10>
			<x11>393</x11>
			<y11>568</y11>
			<x12>418</x12>
			<y12>576</y12>
			<x13>431</x13>
			<y13>589</y13>
			<x14>444</x14>
			<y14>590</y14>
			<x15>553</x15>
			<y15>296</y15>
			<x16>555</x16>
			<y16>281</y16>
			<x17>544</x17>
			<y17>270</y17>
			<x18>543</x18>
			<y18>263</y18>
			<x19>573</x19>
			<y19>190</y19>
			<x20>581</x20>
			<y20>153</y20>
			<x21>565</x21>
			<y21>146</y21>
			<x22>555</x22>
			<y22>148</y22>
			<x23>564</x23>
			<y23>115</y23>
			<x24>531</x24>
			<y24>91</y24>
			<x25>466</x25>
			<y25>75</y25>
			<x26>450</x26>
			<y26>112</y26>
			<x27>442</x27>
			<y27>114</y27>
			<x28>340</x28>
			<y28>86</y28>
			<x29>316</x29>
			<y29>66</y29>
			<x30>263</x30>
			<y30>50</y30>
			<x31>258</x31>
			<y31>50</y31>
			<x32>250</x32>
			<y32>63</y32>
			<x33>232</x33>
			<y33>57</y33>
			<x34>221</x34>
			<y34>62</y34>
			<x35>109</x35>
			<y35>399</y35>
		</polygon>
	</object>
</annotation>
