<annotation>
	<folder></folder>
	<filename>jetson_nano_35_jpg.rf.68f6444f2f3a7ac547e3fe8c0d70bfe7.jpg</filename>
	<path>jetson_nano_35_jpg.rf.68f6444f2f3a7ac547e3fe8c0d70bfe7.jpg</path>
	<source>
		<database>roboflow.com</database>
	</source>
	<size>
		<width>640</width>
		<height>640</height>
		<depth>3</depth>
	</size>
	<segmented>0</segmented>
	<object>
		<name>Jetson Nano</name>
		<pose>Unspecified</pose>
		<truncated>0</truncated>
		<difficult>0</difficult>
		<occluded>0</occluded>
		<bndbox>
			<xmin>43</xmin>
			<xmax>341</xmax>
			<ymin>326</ymin>
			<ymax>561</ymax>
		</bndbox>
		<polygon>
			<x1>201.167513</x1>
			<y1>347.884941</y1>
			<x2>185.939086</x2>
			<y2>352.622673</y2>
			<x3>186.954315</x3>
			<y3>342.470389</y3>
			<x4>174.771574</x4>
			<y4>348.56176</y4>
			<x5>170.71066</x5>
			<y5>336.379019</y5>
			<x6>161.573604</x6>
			<y6>339.763113</y6>
			<x7>157.51269</x7>
			<y7>331.641285</y7>
			<x8>138.730964</x8>
			<y8>324.873096</y8>
			<x9>61.06599</x9>
			<y9>409.475465</y9>
			<x10>74.263959</x10>
			<y10>414.890017</y10>
			<x11>69.187817</x11>
			<y11>420.304568</y11>
			<x12>65.126904</x12>
			<y12>429.103215</y12>
			<x13>67.958656</x13>
			<y13>436.175711</y13>
			<x14>66.925065</x14>
			<y14>439.276485</y14>
			<x15>71.059432</x15>
			<y15>446.167097</y15>
			<x16>63.049096</x16>
			<y16>453.746771</y16>
			<x17>63.049096</x17>
			<y17>472.695952</y17>
			<x18>42.377261</x18>
			<y18>494.056848</y18>
			<x19>235.685279</x19>
			<y19>559.729272</y19>
			<x20>340.253807</x20>
			<y20>402.030457</y20>
			<x21>331.624365</x21>
			<y21>398.646363</y21>
			<x22>330.101523</x22>
			<y22>394.585448</y22>
			<x23>222.994924</x23>
			<y23>363.451776</y23>
			<x24>229.086294</x24>
			<y24>352.622673</y24>
			<x25>208.274112</x25>
			<y25>347.884941</y25>
			<x26>201.167513</x26>
			<y26>356.683587</y26>
			<x27>201.167513</x27>
			<y27>347.884941</y27>
		</polygon>
	</object>
</annotation>
